nano_whale/main.py
nano_whale-0.1.20.dist-info/METADATA
nano_whale-0.1.20.dist-info/WHEEL
nano_whale-0.1.20.dist-info/entry_points.txt
nano_whale-0.1.20.dist-info/licenses/LICENSE
nano_whale-0.1.20.dist-info/RECORD
