Metadata-Version: 2.4
Name: nano-whale
Version: 0.1.20
Summary: A lightweight Terminal User Interface (TUI) for managing Docker containers, images, and volumes via WSL2
Project-URL: Homepage, https://github.com/Vriddhachalam/nano-whale.git
Project-URL: Repository, https://github.com/Vriddhachalam/nano-whale.git
Project-URL: Issues, https://github.com/Vriddhachalam/nano-whale/issues
Project-URL: Documentation, https://github.com/Vriddhachalam/nano-whale/blob/master/README.md
Author-email: Vriddhachalam S <svriddhachalam@gmail.com>
License: MIT License
License-File: LICENSE
Keywords: cli,containers,docker,terminal,textual,tui,wsl2
Classifier: Development Status :: 4 - Beta
Classifier: Environment :: Console
Classifier: Intended Audience :: Developers
Classifier: Intended Audience :: System Administrators
Classifier: License :: OSI Approved :: MIT License
Classifier: Operating System :: Microsoft :: Windows
Classifier: Programming Language :: Python :: 3
Classifier: Programming Language :: Python :: 3.8
Classifier: Programming Language :: Python :: 3.9
Classifier: Programming Language :: Python :: 3.10
Classifier: Programming Language :: Python :: 3.11
Classifier: Programming Language :: Python :: 3.12
Classifier: Topic :: System :: Monitoring
Classifier: Topic :: System :: Systems Administration
Classifier: Topic :: Utilities
Requires-Python: >=3.8
Requires-Dist: textual>=0.40.0
